<?xml version="1.0" encoding="UTF-8"?>
<!--

    Description: A generated data access implementation of entity ContractExt.
                 Generated at 2014-08-26 15:20:27, do NOT modify!
    Author: <a href="mailto:DL88250@gmail.com">Liang Ding</a>
    Version: 1.0.0.0, Aug 26, 2014

-->
<!DOCTYPE mapper PUBLIC "-//mybatis.org//DTD Mapper 3.0//EN" "http://mybatis.org/dtd/mybatis-3-mapper.dtd" >
<mapper namespace="com.epicsaas.app.crm.dao.gen.ContractExtGeneratedMapper" >
  <resultMap id="BaseResultMap" type="com.epicsaas.app.crm.appobject.ContractExtAO" >
    <!--
      WARNING - @mbggenerated
      This element is automatically generated by MyBatis Generator, do not modify.
    -->
    <id column="id" property="id" jdbcType="BIGINT" />
    <result column="contract_id" property="companyId" jdbcType="BIGINT" />
    <result column="dfile_id" property="dfileId" jdbcType="VARCHAR" />
    <result column="dfile_name" property="dfileName" jdbcType="VARCHAR" />
    <result column="dfile_size" property="dfileSize" jdbcType="VARCHAR" />
    <result column="remark" property="remark" jdbcType="VARCHAR" />
  </resultMap>
  <sql id="Criteria_Where_Clause" >
    <!--
      WARNING - @mbggenerated
      This element is automatically generated by MyBatis Generator, do not modify.
    -->
    <where >
      <foreach collection="oredCriteria" item="criteria" separator="or" >
        <if test="criteria.valid" >
          <trim prefix="(" suffix=")" prefixOverrides="and" >
            <foreach collection="criteria.criteria" item="criterion" >
              <choose >
                <when test="criterion.noValue" >
                  and ${criterion.condition}
                </when>
                <when test="criterion.singleValue" >
                  and ${criterion.condition} #{criterion.value}
                </when>
                <when test="criterion.betweenValue" >
                  and ${criterion.condition} #{criterion.value} and #{criterion.secondValue}
                </when>
                <when test="criterion.listValue" >
                  and ${criterion.condition}
                  <foreach collection="criterion.value" item="listItem" open="(" close=")" separator="," >
                    #{listItem}
                  </foreach>
                </when>
              </choose>
            </foreach>
          </trim>
        </if>
      </foreach>
    </where>
  </sql>
  <sql id="Update_By_Criteria_Where_Clause" >
    <!--
      WARNING - @mbggenerated
      This element is automatically generated by MyBatis Generator, do not modify.
    -->
    <where >
      <foreach collection="example.oredCriteria" item="criteria" separator="or" >
        <if test="criteria.valid" >
          <trim prefix="(" suffix=")" prefixOverrides="and" >
            <foreach collection="criteria.criteria" item="criterion" >
              <choose >
                <when test="criterion.noValue" >
                  and ${criterion.condition}
                </when>
                <when test="criterion.singleValue" >
                  and ${criterion.condition} #{criterion.value}
                </when>
                <when test="criterion.betweenValue" >
                  and ${criterion.condition} #{criterion.value} and #{criterion.secondValue}
                </when>
                <when test="criterion.listValue" >
                  and ${criterion.condition}
                  <foreach collection="criterion.value" item="listItem" open="(" close=")" separator="," >
                    #{listItem}
                  </foreach>
                </when>
              </choose>
            </foreach>
          </trim>
        </if>
      </foreach>
    </where>
  </sql>
  <sql id="Base_Column_List" >
    <!--
      WARNING - @mbggenerated
      This element is automatically generated by MyBatis Generator, do not modify.
    -->
    id, contract_id, dfile_id, dfile_name, dfile_size, remark
  </sql>
  <select id="selectByCriteria" resultMap="BaseResultMap" parameterType="com.epicsaas.app.crm.entity.gen.ContractExtCriteria" >
    <!--
      WARNING - @mbggenerated
      This element is automatically generated by MyBatis Generator, do not modify.
    -->
    select
    <if test="distinct" >
      distinct
    </if>
    <include refid="Base_Column_List" />
    from t_crm_contract_ext
    <if test="_parameter != null" >
      <include refid="Criteria_Where_Clause" />
    </if>
    <if test="orderByClause != null" >
      order by ${orderByClause}
    </if>
    <if test="page != null" >
      limit #{page.begin} , #{page.length}
    </if>
  </select>
  <select id="selectByPrimaryKey" resultMap="BaseResultMap" parameterType="String" >
    <!--
      WARNING - @mbggenerated
      This element is automatically generated by MyBatis Generator, do not modify.
    -->
    select 
    <include refid="Base_Column_List" />
    from t_crm_contract_ext
    where id = #{id,jdbcType=BIGINT}
  </select>
  <delete id="deleteByPrimaryKey" parameterType="String" >
    <!--
      WARNING - @mbggenerated
      This element is automatically generated by MyBatis Generator, do not modify.
    -->
    delete from t_crm_contract_ext
    where id = #{id,jdbcType=BIGINT}
  </delete>
  <delete id="deleteByCriteria" parameterType="com.epicsaas.app.crm.entity.gen.ContractExtCriteria" >
    <!--
      WARNING - @mbggenerated
      This element is automatically generated by MyBatis Generator, do not modify.
    -->
    delete from t_crm_contract_ext
    <if test="_parameter != null" >
      <include refid="Criteria_Where_Clause" />
    </if>
  </delete>
  <insert id="insert" parameterType="com.epicsaas.app.crm.appobject.ContractExtAO" >
    <!--
      WARNING - @mbggenerated
      This element is automatically generated by MyBatis Generator, do not modify.
    -->
    <selectKey resultType="String" keyProperty="id" order="BEFORE" >
      select uuid_short()
    </selectKey>
    insert into t_crm_contract_ext (id, contract_id, dfile_id, 
      dfile_name, dfile_size, remark
      )
    values (#{id,jdbcType=BIGINT}, #{companyId,jdbcType=BIGINT}, #{dfileId,jdbcType=VARCHAR}, 
      #{dfileName,jdbcType=VARCHAR}, #{dfileSize,jdbcType=VARCHAR}, #{remark,jdbcType=VARCHAR}
      )
  </insert>
  <insert id="insertSelective" parameterType="com.epicsaas.app.crm.appobject.ContractExtAO" >
    <!--
      WARNING - @mbggenerated
      This element is automatically generated by MyBatis Generator, do not modify.
    -->
    <selectKey resultType="String" keyProperty="id" order="BEFORE" >
      select uuid_short()
    </selectKey>
    insert into t_crm_contract_ext
    <trim prefix="(" suffix=")" suffixOverrides="," >
      id,
      <if test="companyId != null" >
        contract_id,
      </if>
      <if test="dfileId != null" >
        dfile_id,
      </if>
      <if test="dfileName != null" >
        dfile_name,
      </if>
      <if test="dfileSize != null" >
        dfile_size,
      </if>
      <if test="remark != null" >
        remark,
      </if>
    </trim>
    <trim prefix="values (" suffix=")" suffixOverrides="," >
      #{id,jdbcType=BIGINT},
      <if test="companyId != null" >
        #{companyId,jdbcType=BIGINT},
      </if>
      <if test="dfileId != null" >
        #{dfileId,jdbcType=VARCHAR},
      </if>
      <if test="dfileName != null" >
        #{dfileName,jdbcType=VARCHAR},
      </if>
      <if test="dfileSize != null" >
        #{dfileSize,jdbcType=VARCHAR},
      </if>
      <if test="remark != null" >
        #{remark,jdbcType=VARCHAR},
      </if>
    </trim>
  </insert>
  <select id="countByCriteria" parameterType="com.epicsaas.app.crm.entity.gen.ContractExtCriteria" resultType="java.lang.Integer" >
    <!--
      WARNING - @mbggenerated
      This element is automatically generated by MyBatis Generator, do not modify.
    -->
    select count(*) from t_crm_contract_ext
    <if test="_parameter != null" >
      <include refid="Criteria_Where_Clause" />
    </if>
  </select>
  <update id="updateByCriteriaSelective" parameterType="map" >
    <!--
      WARNING - @mbggenerated
      This element is automatically generated by MyBatis Generator, do not modify.
    -->
    update t_crm_contract_ext
    <set >
      <if test="record.id != null" >
        id = #{record.id,jdbcType=BIGINT},
      </if>
      <if test="record.companyId != null" >
        contract_id = #{record.companyId,jdbcType=BIGINT},
      </if>
      <if test="record.dfileId != null" >
        dfile_id = #{record.dfileId,jdbcType=VARCHAR},
      </if>
      <if test="record.dfileName != null" >
        dfile_name = #{record.dfileName,jdbcType=VARCHAR},
      </if>
      <if test="record.dfileSize != null" >
        dfile_size = #{record.dfileSize,jdbcType=VARCHAR},
      </if>
      <if test="record.remark != null" >
        remark = #{record.remark,jdbcType=VARCHAR},
      </if>
    </set>
    <if test="_parameter != null" >
      <include refid="Update_By_Criteria_Where_Clause" />
    </if>
  </update>
  <update id="updateByCriteria" parameterType="map" >
    <!--
      WARNING - @mbggenerated
      This element is automatically generated by MyBatis Generator, do not modify.
    -->
    update t_crm_contract_ext
    set id = #{record.id,jdbcType=BIGINT},
      contract_id = #{record.companyId,jdbcType=BIGINT},
      dfile_id = #{record.dfileId,jdbcType=VARCHAR},
      dfile_name = #{record.dfileName,jdbcType=VARCHAR},
      dfile_size = #{record.dfileSize,jdbcType=VARCHAR},
      remark = #{record.remark,jdbcType=VARCHAR}
    <if test="_parameter != null" >
      <include refid="Update_By_Criteria_Where_Clause" />
    </if>
  </update>
  <update id="updateByPrimaryKeySelective" parameterType="com.epicsaas.app.crm.appobject.ContractExtAO" >
    <!--
      WARNING - @mbggenerated
      This element is automatically generated by MyBatis Generator, do not modify.
    -->
    update t_crm_contract_ext
    <set >
      <if test="companyId != null" >
        contract_id = #{companyId,jdbcType=BIGINT},
      </if>
      <if test="dfileId != null" >
        dfile_id = #{dfileId,jdbcType=VARCHAR},
      </if>
      <if test="dfileName != null" >
        dfile_name = #{dfileName,jdbcType=VARCHAR},
      </if>
      <if test="dfileSize != null" >
        dfile_size = #{dfileSize,jdbcType=VARCHAR},
      </if>
      <if test="remark != null" >
        remark = #{remark,jdbcType=VARCHAR},
      </if>
    </set>
    where id = #{id,jdbcType=BIGINT}
  </update>
  <update id="updateByPrimaryKey" parameterType="com.epicsaas.app.crm.appobject.ContractExtAO" >
    <!--
      WARNING - @mbggenerated
      This element is automatically generated by MyBatis Generator, do not modify.
    -->
    update t_crm_contract_ext
    set contract_id = #{companyId,jdbcType=BIGINT},
      dfile_id = #{dfileId,jdbcType=VARCHAR},
      dfile_name = #{dfileName,jdbcType=VARCHAR},
      dfile_size = #{dfileSize,jdbcType=VARCHAR},
      remark = #{remark,jdbcType=VARCHAR}
    where id = #{id,jdbcType=BIGINT}
  </update>
</mapper>